test_wevvv/__init__.py
test_wevvv/core.py
test_wevvv/log.py
test_wevvv/server.py
test_wevvv-0.1.1.dist-info/METADATA
test_wevvv-0.1.1.dist-info/WHEEL
test_wevvv-0.1.1.dist-info/top_level.txt
test_wevvv-0.1.1.dist-info/RECORD
